whitebox_plugin_device_status/__init__.py
whitebox_plugin_device_status/jsx/GPSStatus.jsx
whitebox_plugin_device_status/jsx/GPSStatus.test.jsx
whitebox_plugin_device_status/jsx/SDRStatus.jsx
whitebox_plugin_device_status/jsx/SDRStatus.test.jsx
whitebox_plugin_device_status/jsx/stores/devices.js
whitebox_plugin_device_status/jsx/stores/devices.test.js
whitebox_plugin_device_status/whitebox_plugin_device_status.py
whitebox_test_plugin_device_status/__init__.py
whitebox_test_plugin_device_status/federation/gps_status.spec.js
whitebox_test_plugin_device_status/federation/sdr_status.spec.js
whitebox_test_plugin_device_status/test_whitebox_plugin_device_status.py
whitebox_plugin_device_status-0.1.8.dist-info/LICENSE
whitebox_plugin_device_status-0.1.8.dist-info/METADATA
whitebox_plugin_device_status-0.1.8.dist-info/WHEEL
whitebox_plugin_device_status-0.1.8.dist-info/RECORD
